.gitignore
MANIFEST.in
README.rst
requirements.txt
setup.py
docs/HISTORY.txt
docs/LICENSE
pixiv/__init__.py
pixiv/downloader/__init__.py
pixiv/downloader/cli.py
pixiv/downloader/downloader.py
pixivdownloader.egg-info/PKG-INFO
pixivdownloader.egg-info/SOURCES.txt
pixivdownloader.egg-info/dependency_links.txt
pixivdownloader.egg-info/entry_points.txt
pixivdownloader.egg-info/namespace_packages.txt
pixivdownloader.egg-info/not-zip-safe
pixivdownloader.egg-info/requires.txt
pixivdownloader.egg-info/top_level.txt