Metadata-Version: 1.2
Name: pixivdownloader
Version: 0.1.0
Summary: Download posts from pixiv.net via CLI, CLI UI or programmatically.
Home-page: https://github.com/Nachtalb/PixivDownloader
Author: Nachtalb
Maintainer: Nachtalb
License: GPL3
Keywords: pixiv downloader
Platform: UNKNOWN
Classifier: Programming Language :: Python
Classifier: Programming Language :: Python :: 3.7
Classifier: License :: OSI Approved :: GNU Lesser General Public License v3 (LGPLv3)
